{
  "colorPrimary": {
    "value": "#1f5644",
    "type": "color"
  },
  "colorSecondary": {
    "value": "#daeae8",
    "type": "color"
  },
  "colorAccent": {
    "value": "#00aaa5",
    "type": "color"
  },
  "colorBackground": {
    "value": "#fefefe",
    "type": "color"
  },
  "colorSurface": {
    "value": "#e4e4e4",
    "type": "color"
  },
  "colorError": {
    "value": "#b00020",
    "type": "color"
  },
  "colorOnPrimary": {
    "value": "#fefefe",
    "type": "color"
  },
  "colorOnSecondary": {
    "value": "#010101",
    "type": "color"
  },
  "colorOnAccent": {
    "value": "#fefefe",
    "type": "color"
  },
  "colorOnBackground": {
    "value": "#010101",
    "type": "color"
  },
  "colorOnSurface": {
    "value": "#010101",
    "type": "color"
  },
  "colorOnError": {
    "value": "#fefefe",
    "type": "color"
  },
  "colorTextDarkPrimary": {
    "type": "color",
    "value": "rgba(0, 0, 0, 0.87)"
  },
  "colorTextDarkSecondary": {
    "type": "color",
    "value": "rgba(0, 0, 0, 0.6)"
  },
  "colorTextDarkHint": {
    "type": "color",
    "value": "rgba(0, 0, 0, 0.38)"
  },
  "colorTextDarkDisabled": {
    "type": "color",
    "value": "rgba(0, 0, 0, 0.38)"
  },
  "colorTextDarkIcon": {
    "type": "color",
    "value": "rgba(0, 0, 0, 0.38)"
  },
  "colorTextLightPrimary": {
    "type": "color",
    "value": "rgba(255, 255, 255, 1)"
  },
  "colorTextLightSecondary": {
    "type": "color",
    "value": "rgba(255, 255, 255, 0.7)"
  },
  "colorTextLightHint": {
    "type": "color",
    "value": "rgba(255, 255, 255, 0.5)"
  },
  "colorTextLightDisabled": {
    "type": "color",
    "value": "rgba(255, 255, 255, 0.5)"
  },
  "colorTextLightIcon": {
    "type": "color",
    "value": "rgba(255, 255, 255, 0.5)"
  },
  "fontFamilyH1": {
    "usage": "",
    "value": "Galano, Verdana, sans-serif",
    "type": "font-family"
  },
  "fontFamilyH2": {
    "usage": "",
    "value": "Galano, Verdana, sans-serif",
    "type": "font-family"
  },
  "fontFamilyH3": {
    "usage": "",
    "value": "Galano, Verdana, sans-serif",
    "type": "font-family"
  },
  "fontFamilyH4": {
    "usage": "",
    "value": "Galano, Verdana, sans-serif",
    "type": "font-family"
  },
  "fontFamilyH5": {
    "usage": "",
    "value": "Galano, Verdana, sans-serif",
    "type": "font-family"
  },
  "fontFamilyH6": {
    "usage": "",
    "value": "Galano, Verdana, sans-serif",
    "type": "font-family"
  },
  "fontFamilySubtitle": {
    "usage": "",
    "value": "Maison Nueue, Helvetica, sans-serif",
    "type": "font-family"
  },
  "fontFamilySubtitleSmall": {
    "usage": "",
    "value": "Maison Nueue, Helvetica, sans-serif",
    "type": "font-family"
  },
  "fontFamilyBody": {
    "usage": "",
    "value": "Maison Nueue, Helvetica, sans-serif",
    "type": "font-family"
  },
  "fontFamilyBodySmall": {
    "usage": "",
    "value": "Maison Nueue, Helvetica, sans-serif",
    "type": "font-family"
  },
  "fontFamilyButton": {
    "usage": "",
    "value": "Maison Nueue, Helvetica, sans-serif",
    "type": "font-family"
  },
  "fontFamilyCaption": {
    "usage": "",
    "value": "Maison Nueue, Helvetica, sans-serif",
    "type": "font-family"
  },
  "fontFamilyOverline": {
    "usage": "",
    "value": "Maison Nueue, Helvetica, sans-serif",
    "type": "font-family"
  },
  "fontWeightH1": {
    "usage": "",
    "value": 300,
    "type": "font-weight"
  },
  "fontWeightH2": {
    "usage": "",
    "value": 300,
    "type": "font-weight"
  },
  "fontWeightH3": {
    "usage": "",
    "value": 400,
    "type": "font-weight"
  },
  "fontWeightH4": {
    "usage": "",
    "value": 400,
    "type": "font-weight"
  },
  "fontWeightH5": {
    "usage": "",
    "value": 400,
    "type": "font-weight"
  },
  "fontWeightH6": {
    "usage": "",
    "value": 500,
    "type": "font-weight"
  },
  "fontWeightSubtitle": {
    "usage": "",
    "value": 400,
    "type": "font-weight"
  },
  "fontWeightSubtitleSmall": {
    "usage": "",
    "value": 500,
    "type": "font-weight"
  },
  "fontWeightBody": {
    "usage": "",
    "value": 400,
    "type": "font-weight"
  },
  "fontWeightBodySmall": {
    "usage": "",
    "value": 400,
    "type": "font-weight"
  },
  "fontWeightButton": {
    "usage": "",
    "value": 500,
    "type": "font-weight"
  },
  "fontWeightCaption": {
    "usage": "",
    "value": 400,
    "type": "font-weight"
  },
  "fontWeightOverline": {
    "usage": "",
    "value": 400,
    "type": "font-weight"
  },
  "fontSizeH1": {
    "usage": "",
    "value": "6rem",
    "type": "font-size"
  },
  "fontSizeH2": {
    "usage": "",
    "value": "3.75rem",
    "type": "font-size"
  },
  "fontSizeH3": {
    "usage": "",
    "value": "3rem",
    "type": "font-size"
  },
  "fontSizeH4": {
    "usage": "",
    "value": "2.125rem",
    "type": "font-size"
  },
  "fontSizeH5": {
    "usage": "",
    "value": "1.5rem",
    "type": "font-size"
  },
  "fontSizeH6": {
    "usage": "",
    "value": "1.25rem",
    "type": "font-size"
  },
  "fontSizeSubtitle": {
    "usage": "",
    "value": "1rem",
    "type": "font-size"
  },
  "fontSizeSubtitleSmall": {
    "usage": "",
    "value": "0.875rem",
    "type": "font-size"
  },
  "fontSizeBody": {
    "usage": "",
    "value": "1rem",
    "type": "font-size"
  },
  "fontSizeBodySmall": {
    "usage": "",
    "value": "0.875rem",
    "type": "font-size"
  },
  "fontSizeButton": {
    "usage": "",
    "value": "0.875rem",
    "type": "font-size"
  },
  "fontSizeCaption": {
    "usage": "",
    "value": "0.75rem",
    "type": "font-size"
  },
  "fontSizeOverline": {
    "usage": "",
    "value": "0.625rem",
    "type": "font-size"
  },
  "durationSimpleSmall": {
    "usage": "For things like switches, control boxes, etc...",
    "value": "0.1s",
    "type": "time"
  },
  "durationSimpleSmallEnter": {
    "usage": "For small dialogs, alerts, etc...",
    "value": ".15s",
    "type": "time"
  },
  "durationSimpleSmallExit": {
    "usage": "For small dialogs, alerts, etc...",
    "value": "0.075s",
    "type": "time"
  },
  "durationSimpleMedium": {
    "usage": "For card transforms, etc...",
    "value": "0.225s",
    "type": "time"
  },
  "durationSimpleMediumEnter": {
    "usage": "For card transforms, etc...",
    "value": "0.25s",
    "type": "time"
  },
  "durationSimpleMediumExit": {
    "usage": "For card transforms, etc...",
    "value": "0.2s",
    "type": "time"
  },
  "durationSimpleLarge": {
    "usage": "For page transforms, etc...",
    "value": "0.275s",
    "type": "time"
  },
  "durationSimpleLargeEnter": {
    "usage": "For card transforms, etc...",
    "value": "0.3s",
    "type": "time"
  },
  "durationSimpleLargeExit": {
    "usage": "For card transforms, etc...",
    "value": "0.25s",
    "type": "time"
  },
  "timingCurveDecelerate": {
    "value": "cubic-bezier(0, 0, .2, 1)",
    "type": "timing function"
  },
  "timingCurveAccelerate": {
    "value": "cubic-bezier(.4, 0, 1, 1)",
    "type": "timing function"
  },
  "timingCurveStandard": {
    "value": "cubic-bezier(.4, 0, .2, 1)",
    "type": "timing function"
  },
  "timingCurveSharp": {
    "value": "cubic-bezier(.4, 0, .6, 1)",
    "type": "timing function"
  },
  "elevationZHidden": {
    "usage": "For items that should be on the page but not visible",
    "value": -1,
    "type": "z-index"
  },
  "elevationZDefault": {
    "usage": "Used for setting a standard z-index",
    "value": 1,
    "type": "z-index"
  },
  "elevationZDropdown": {
    "usage": "used for dropdowns",
    "value": 1000,
    "type": "z-index"
  },
  "elevationZOverlay": {
    "usage": "Used for overlays and things that are supposed to mask the page so that other things above them can be afforded visual focus",
    "value": 5000,
    "type": "z-index"
  },
  "elevationZModal": {
    "usage": "For popups and other modal elements with a high elevation",
    "value": 6000,
    "type": "z-index"
  },
  "emphasisHigh": {
    "usage": "Use for more prominent text",
    "type": "alpha",
    "value": 0.87
  },
  "emphasisMedium": {
    "usage": "Use for secondary text",
    "type": "alpha",
    "value": 0.6
  },
  "emphasisDisabled": {
    "usage": "Use for hints and things that are disabled",
    "type": "alpha",
    "value": 0.38
  }
}